napari_tmidas/__init__.py
napari_tmidas/_crop_anything.py
napari_tmidas/_env_manager.py
napari_tmidas/_file_conversion.py
napari_tmidas/_file_selector.py
napari_tmidas/_label_inspection.py
napari_tmidas/_processing_worker.py
napari_tmidas/_reader.py
napari_tmidas/_registry.py
napari_tmidas/_roi_colocalization.py
napari_tmidas/_sample_data.py
napari_tmidas/_ui_utils.py
napari_tmidas/_version.py
napari_tmidas/_widget.py
napari_tmidas/_writer.py
napari_tmidas/napari.yaml
napari_tmidas/_tests/test_crop_anything.py
napari_tmidas/_tests/test_env_manager.py
napari_tmidas/_tests/test_file_selector.py
napari_tmidas/_tests/test_grid_view_overlay.py
napari_tmidas/_tests/test_init.py
napari_tmidas/_tests/test_intensity_label_filter.py
napari_tmidas/_tests/test_label_inspection.py
napari_tmidas/_tests/test_processing_basic.py
napari_tmidas/_tests/test_processing_worker.py
napari_tmidas/_tests/test_reader.py
napari_tmidas/_tests/test_regionprops_analysis.py
napari_tmidas/_tests/test_registry.py
napari_tmidas/_tests/test_sample_data.py
napari_tmidas/_tests/test_scipy_filters.py
napari_tmidas/_tests/test_skimage_filters.py
napari_tmidas/_tests/test_split_channels.py
napari_tmidas/_tests/test_spotiflow.py
napari_tmidas/_tests/test_tyx_display_fix.py
napari_tmidas/_tests/test_ui_utils.py
napari_tmidas/_tests/test_widget.py
napari_tmidas/_tests/test_windows_basic.py
napari_tmidas/_tests/test_writer.py
napari_tmidas/processing_functions/__init__.py
napari_tmidas/processing_functions/basic.py
napari_tmidas/processing_functions/careamics_denoising.py
napari_tmidas/processing_functions/careamics_env_manager.py
napari_tmidas/processing_functions/cellpose_env_manager.py
napari_tmidas/processing_functions/cellpose_segmentation.py
napari_tmidas/processing_functions/colocalization.py
napari_tmidas/processing_functions/file_compression.py
napari_tmidas/processing_functions/grid_view_overlay.py
napari_tmidas/processing_functions/intensity_label_filter.py
napari_tmidas-0.2.6.dist-info/licenses/LICENSE
napari_tmidas-0.2.6.dist-info/METADATA
napari_tmidas-0.2.6.dist-info/WHEEL
napari_tmidas-0.2.6.dist-info/entry_points.txt
napari_tmidas-0.2.6.dist-info/top_level.txt
napari_tmidas-0.2.6.dist-info/RECORD
