Metadata-Version: 2.4
Name: napari-tmidas
Version: 0.2.6
Summary: A plugin for batch processing of confocal and whole-slide microscopy images of biological tissues
Author: Marco Meer
Author-email: marco.meer@pm.me
License: 
Project-URL: Bug Tracker, https://github.com/macromeer/napari-tmidas/issues
Project-URL: Documentation, https://github.com/macromeer/napari-tmidas#README.md
Project-URL: Source Code, https://github.com/macromeer/napari-tmidas
Project-URL: User Support, https://github.com/macromeer/napari-tmidas/issues
Classifier: Development Status :: 2 - Pre-Alpha
Classifier: Framework :: napari
Classifier: Intended Audience :: Developers
Classifier: License :: OSI Approved :: BSD License
Classifier: Operating System :: MacOS
Classifier: Operating System :: POSIX :: Linux
Classifier: Programming Language :: Python
Classifier: Programming Language :: Python :: 3
Classifier: Programming Language :: Python :: 3 :: Only
Classifier: Programming Language :: Python :: 3.10
Classifier: Programming Language :: Python :: 3.11
Classifier: Topic :: Scientific/Engineering :: Image Processing
Requires-Python: >=3.10
License-File: LICENSE
Requires-Dist: numpy<2.0,>=1.23.0
Requires-Dist: magicgui
Requires-Dist: tqdm
Requires-Dist: qtpy
Requires-Dist: scikit-image>=0.19.0
Requires-Dist: scikit-learn-extra>=0.3.0
Requires-Dist: pyqt5
Requires-Dist: zarr
Requires-Dist: ome-zarr
Requires-Dist: napari-ome-zarr
Requires-Dist: nd2
Requires-Dist: pylibCZIrw
Requires-Dist: readlif
Requires-Dist: tiffslide
Requires-Dist: acquifer-napari
Provides-Extra: testing
Requires-Dist: tox; extra == "testing"
Requires-Dist: pytest>=7.0.0; extra == "testing"
Requires-Dist: pytest-cov; extra == "testing"
Requires-Dist: pytest-qt; extra == "testing"
Requires-Dist: pytest-timeout; extra == "testing"
Requires-Dist: napari; extra == "testing"
Requires-Dist: pyqt5; extra == "testing"
Requires-Dist: psygnal>=0.8.0; extra == "testing"
Provides-Extra: clustering
Requires-Dist: scikit-learn-extra>=0.3.0; extra == "clustering"
Provides-Extra: deep-learning
Requires-Dist: torch>=1.12.0; extra == "deep-learning"
Requires-Dist: torchvision>=0.13.0; extra == "deep-learning"
Requires-Dist: timm; extra == "deep-learning"
Requires-Dist: opencv-python; extra == "deep-learning"
Requires-Dist: cmake; extra == "deep-learning"
Requires-Dist: hydra-core; extra == "deep-learning"
Requires-Dist: eva-decord; extra == "deep-learning"
Provides-Extra: all
Requires-Dist: napari-tmidas[clustering,deep-learning,testing]; extra == "all"
Dynamic: license-file
